odoo/addons/partner_category_type/README.rst
odoo/addons/partner_category_type/__init__.py
odoo/addons/partner_category_type/__manifest__.py
odoo/addons/partner_category_type/i18n/it.po
odoo/addons/partner_category_type/i18n/partner_category_type.pot
odoo/addons/partner_category_type/models/__init__.py
odoo/addons/partner_category_type/models/res_partner_category.py
odoo/addons/partner_category_type/readme/CONTRIBUTORS.md
odoo/addons/partner_category_type/readme/DESCRIPTION.md
odoo/addons/partner_category_type/static/description/icon.png
odoo/addons/partner_category_type/static/description/index.html
odoo/addons/partner_category_type/tests/__init__.py
odoo/addons/partner_category_type/tests/test_partner_category_type.py
odoo/addons/partner_category_type/views/res_partner_category_views.xml
odoo_addon_partner_category_type-18.0.1.0.0.2.dist-info/METADATA
odoo_addon_partner_category_type-18.0.1.0.0.2.dist-info/WHEEL
odoo_addon_partner_category_type-18.0.1.0.0.2.dist-info/top_level.txt
odoo_addon_partner_category_type-18.0.1.0.0.2.dist-info/RECORD
